{
  "models": {
    "vmSub_TestimonialCarouselTestimonial": {
      "storeContentAs": {
        "$type": "YuzuDelivery.Umbraco.Import.GlobalStoreContentAs, YuzuDelivery.Umbraco.Import",
        "parentContentId": "1081",
        "addAreaNode": false,
        "primaryPropertyName": "personName",
        "propertyPrefix": null,
        "type": 1,
        "groupName": null
      },
      "documentTypeAlias": "testimonial",
      "properties": {}
    },
    "vmBlock_ServiceSummary": {
      "storeContentAs": {
        "$type": "YuzuDelivery.Umbraco.Import.GlobalStoreContentAs, YuzuDelivery.Umbraco.Import",
        "parentContentId": "1070",
        "addAreaNode": false,
        "primaryPropertyName": "title",
        "propertyPrefix": null,
        "type": 1,
        "groupName": ""
      },
      "documentTypeAlias": "service",
      "properties": {}
    },
    "vmBlock_ImageFeature": {
      "storeContentAs": {
        "$type": "YuzuDelivery.Umbraco.Import.GlobalStoreContentAs, YuzuDelivery.Umbraco.Import",
        "parentContentId": "1070",
        "addAreaNode": false,
        "primaryPropertyName": "title",
        "propertyPrefix": null,
        "type": 1,
        "groupName": ""
      },
      "documentTypeAlias": "service",
      "properties": {}
    },
    "vmBlock_BlogSummary": {
      "storeContentAs": {
        "$type": "YuzuDelivery.Umbraco.Import.GlobalStoreContentAs, YuzuDelivery.Umbraco.Import",
        "parentContentId": "1069",
        "addAreaNode": false,
        "primaryPropertyName": "title",
        "propertyPrefix": null,
        "type": 1,
        "groupName": null
      },
      "documentTypeAlias": "blog",
      "properties": {}
    },
    "vmSub_BlogSummaryMeta": {
      "storeContentAs": {
        "$type": "YuzuDelivery.Umbraco.Import.GroupStoreContentAs, YuzuDelivery.Umbraco.Import",
        "type": 2,
        "groupName": "Meta"
      },
      "documentTypeAlias": "blog",
      "properties": {
        "Author": 90,
        "Date": 91,
        "Category": 92
      }
    },
    "vmSub_ContactInformationContactDetails": {
      "storeContentAs": {
        "$type": "YuzuDelivery.Umbraco.Import.GroupStoreContentAs, YuzuDelivery.Umbraco.Import",
        "type": 2,
        "groupName": "Contact"
      },
      "documentTypeAlias": "contactInformation",
      "properties": {
        "Sections": 102
      }
    },
    "vmSub_ContactInformationMoreInfo": {
      "storeContentAs": {
        "$type": "YuzuDelivery.Umbraco.Import.GroupStoreContentAs, YuzuDelivery.Umbraco.Import",
        "type": 2,
        "groupName": "More"
      },
      "documentTypeAlias": "contactInformation",
      "properties": {
        "Title": 103,
        "Text": 104,
        "Link": 178
      }
    },
    "vmSub_TeamMember": {
      "storeContentAs": {
        "$type": "YuzuDelivery.Umbraco.Import.GlobalStoreContentAs, YuzuDelivery.Umbraco.Import",
        "parentContentId": "1071",
        "addAreaNode": false,
        "primaryPropertyName": "personName",
        "propertyPrefix": null,
        "type": 1,
        "groupName": null
      },
      "properties": {}
    }
  }
}